{
  "browserless_api_key": "YOUR_BROWSERLESS_API_KEY_HERE",

  "groups": [
    {
      "url": "https://www.meetup.com/example-group/",
      "sales_rep": "John Smith"
    },
    {
      "url": "https://www.meetup.com/another-group/",
      "sales_rep": "Jane Doe"
    }
  ],

  "rep_emails": {
    "John Smith": "john.smith@company.com",
    "Jane Doe": "jane.doe@company.com"
  },

  "territories": {
    "_comment": "Maps city names to sales reps. Event location overrides group assignment.",

    "New York": "Chethan Kosaraju",
    "NYC": "Chethan Kosaraju",
    "Manhattan": "Chethan Kosaraju",
    "Brooklyn": "Chethan Kosaraju",
    "Boston": "Chethan Kosaraju",
    "Cambridge": "Chethan Kosaraju",
    "San Francisco": "Chethan Kosaraju",
    "SF": "Chethan Kosaraju",
    "Mountain View": "Chethan Kosaraju",
    "Palo Alto": "Chethan Kosaraju",
    "San Jose": "Chethan Kosaraju",
    "Sunnyvale": "Chethan Kosaraju",
    "Menlo Park": "Chethan Kosaraju",
    "Cupertino": "Chethan Kosaraju",
    "Oakland": "Chethan Kosaraju",
    "Berkeley": "Chethan Kosaraju",
    "Seattle": "Chethan Kosaraju",
    "Bellevue": "Chethan Kosaraju",
    "Redmond": "Chethan Kosaraju",
    "Chicago": "Chethan Kosaraju",
    "Los Angeles": "Chethan Kosaraju",
    "LA": "Chethan Kosaraju",
    "Santa Monica": "Chethan Kosaraju",
    "Denver": "Mikayla Rice-Harvey",
    "Austin": "Mikayla Rice-Harvey",
    "Atlanta": "Mikayla Rice-Harvey",
    "Philadelphia": "Chethan Kosaraju",
    "Washington": "Chethan Kosaraju",
    "DC": "Chethan Kosaraju",

    "Dallas": "Mikayla Rice-Harvey",
    "Fort Worth": "Mikayla Rice-Harvey",
    "DFW": "Mikayla Rice-Harvey",
    "Plano": "Mikayla Rice-Harvey",
    "Irving": "Mikayla Rice-Harvey",
    "Arlington": "Mikayla Rice-Harvey",
    "Houston": "Mikayla Rice-Harvey",
    "San Antonio": "Mikayla Rice-Harvey",

    "Berlin": "Magnus Metz",
    "Munich": "Magnus Metz",
    "München": "Magnus Metz",
    "Muenchen": "Magnus Metz",
    "Frankfurt": "Magnus Metz",
    "Hamburg": "Magnus Metz",
    "Cologne": "Magnus Metz",
    "Köln": "Magnus Metz",
    "Koeln": "Magnus Metz",
    "Düsseldorf": "Magnus Metz",
    "Duesseldorf": "Magnus Metz",
    "Stuttgart": "Magnus Metz",
    "Hannover": "Magnus Metz",
    "Hanover": "Magnus Metz",
    "Leipzig": "Magnus Metz",
    "Dresden": "Magnus Metz",
    "Nuremberg": "Magnus Metz",
    "Nürnberg": "Magnus Metz",
    "Nuernberg": "Magnus Metz",
    "Dortmund": "Magnus Metz",
    "Essen": "Magnus Metz",
    "Bremen": "Magnus Metz",
    "Vienna": "Magnus Metz",
    "Wien": "Magnus Metz",
    "Zurich": "Magnus Metz",
    "Zürich": "Magnus Metz",
    "Zuerich": "Magnus Metz",
    "Bern": "Magnus Metz",
    "Basel": "Magnus Metz",
    "Geneva": "Magnus Metz",
    "Genève": "Magnus Metz",
    "Genf": "Magnus Metz",

    "Barcelona": "Thomas Gerard",
    "Madrid": "Thomas Gerard",
    "Valencia": "Thomas Gerard",
    "Seville": "Thomas Gerard",
    "Sevilla": "Thomas Gerard",
    "Bilbao": "Thomas Gerard",
    "Málaga": "Thomas Gerard",
    "Malaga": "Thomas Gerard",
    "Paris": "Thomas Gerard",
    "Lyon": "Thomas Gerard",
    "Marseille": "Thomas Gerard",
    "Toulouse": "Thomas Gerard",
    "Nice": "Thomas Gerard",
    "Nantes": "Thomas Gerard",
    "Bordeaux": "Thomas Gerard",
    "Lille": "Thomas Gerard",
    "Strasbourg": "Thomas Gerard",
    "Montpellier": "Thomas Gerard",
    "Lisbon": "Thomas Gerard",
    "Lisboa": "Thomas Gerard",
    "Porto": "Thomas Gerard",
    "Milan": "Thomas Gerard",
    "Milano": "Thomas Gerard",
    "Rome": "Thomas Gerard",
    "Roma": "Thomas Gerard",
    "Turin": "Thomas Gerard",
    "Torino": "Thomas Gerard",
    "Florence": "Thomas Gerard",
    "Firenze": "Thomas Gerard",
    "Naples": "Thomas Gerard",
    "Napoli": "Thomas Gerard",
    "Bologna": "Thomas Gerard",

    "Amsterdam": "Bouke van der Meer",
    "Rotterdam": "Bouke van der Meer",
    "The Hague": "Bouke van der Meer",
    "Den Haag": "Bouke van der Meer",
    "Utrecht": "Bouke van der Meer",
    "Eindhoven": "Bouke van der Meer",
    "Stockholm": "Bouke van der Meer",
    "Gothenburg": "Bouke van der Meer",
    "Göteborg": "Bouke van der Meer",
    "Malmö": "Bouke van der Meer",
    "Malmo": "Bouke van der Meer",
    "Copenhagen": "Bouke van der Meer",
    "København": "Bouke van der Meer",
    "Kobenhavn": "Bouke van der Meer",
    "Oslo": "Bouke van der Meer",
    "Helsinki": "Bouke van der Meer",
    "Brussels": "Bouke van der Meer",
    "Bruxelles": "Bouke van der Meer",
    "Brussel": "Bouke van der Meer",
    "Antwerp": "Bouke van der Meer",
    "Antwerpen": "Bouke van der Meer",
    "Ghent": "Bouke van der Meer",
    "Gent": "Bouke van der Meer",

    "London": "Mark Maxwell",
    "Manchester": "Mark Maxwell",
    "Birmingham": "Mark Maxwell",
    "Leeds": "Mark Maxwell",
    "Glasgow": "Mark Maxwell",
    "Edinburgh": "Mark Maxwell",
    "Bristol": "Mark Maxwell",
    "Liverpool": "Mark Maxwell",
    "Newcastle": "Mark Maxwell",
    "Sheffield": "Mark Maxwell",
    "Nottingham": "Mark Maxwell",
    "Cambridge": "Mark Maxwell",
    "Oxford": "Mark Maxwell",
    "Dublin": "Mark Maxwell",
    "Belfast": "Mark Maxwell",
    "Cork": "Mark Maxwell",

    "São Paulo": "Marcos Teixeira",
    "Sao Paulo": "Marcos Teixeira",
    "Rio de Janeiro": "Marcos Teixeira",
    "Rio": "Marcos Teixeira",
    "Brasília": "Marcos Teixeira",
    "Brasilia": "Marcos Teixeira",
    "Belo Horizonte": "Marcos Teixeira",
    "Porto Alegre": "Marcos Teixeira",
    "Curitiba": "Marcos Teixeira",
    "Salvador": "Marcos Teixeira",
    "Recife": "Marcos Teixeira",
    "Fortaleza": "Marcos Teixeira",
    "Buenos Aires": "Marcos Teixeira",
    "Santiago": "Marcos Teixeira",
    "Lima": "Marcos Teixeira",
    "Bogotá": "Marcos Teixeira",
    "Bogota": "Marcos Teixeira",
    "Medellín": "Marcos Teixeira",
    "Medellin": "Marcos Teixeira",
    "Mexico City": "Marcos Teixeira",
    "Ciudad de México": "Marcos Teixeira",
    "CDMX": "Marcos Teixeira",
    "Guadalajara": "Marcos Teixeira",
    "Monterrey": "Marcos Teixeira"
  },

  "timezones": {
    "_comment": "Maps city names to IANA timezone strings for Google Calendar events.",

    "New York": "America/New_York",
    "NYC": "America/New_York",
    "Boston": "America/New_York",
    "Philadelphia": "America/New_York",
    "Washington": "America/New_York",
    "DC": "America/New_York",
    "Atlanta": "America/New_York",

    "Chicago": "America/Chicago",
    "Dallas": "America/Chicago",
    "Houston": "America/Chicago",
    "Austin": "America/Chicago",

    "Denver": "America/Denver",

    "San Francisco": "America/Los_Angeles",
    "Los Angeles": "America/Los_Angeles",
    "Seattle": "America/Los_Angeles",

    "London": "Europe/London",
    "Dublin": "Europe/Dublin",

    "Berlin": "Europe/Berlin",
    "Munich": "Europe/Berlin",
    "Frankfurt": "Europe/Berlin",
    "Vienna": "Europe/Vienna",
    "Zurich": "Europe/Zurich",

    "Paris": "Europe/Paris",
    "Barcelona": "Europe/Madrid",
    "Madrid": "Europe/Madrid",
    "Milan": "Europe/Rome",
    "Rome": "Europe/Rome",
    "Lisbon": "Europe/Lisbon",

    "Amsterdam": "Europe/Amsterdam",
    "Brussels": "Europe/Brussels",
    "Stockholm": "Europe/Stockholm",
    "Copenhagen": "Europe/Copenhagen",
    "Oslo": "Europe/Oslo",
    "Helsinki": "Europe/Helsinki",

    "São Paulo": "America/Sao_Paulo",
    "Rio de Janeiro": "America/Sao_Paulo",
    "Buenos Aires": "America/Argentina/Buenos_Aires",
    "Santiago": "America/Santiago",
    "Lima": "America/Lima",
    "Bogotá": "America/Bogota",
    "Mexico City": "America/Mexico_City"
  },

  "google_sheets": {
    "enabled": false,
    "spreadsheet_id": "YOUR_SPREADSHEET_ID_HERE",
    "credentials_path": "google_credentials.json",
    "worksheet_name": "Events"
  },

  "slack": {
    "enabled": false,
    "webhook_url": "https://hooks.slack.com/services/YOUR/WEBHOOK/URL"
  },

  "calendar": {
    "enabled": false,
    "output_dir": "calendars",
    "default_duration_hours": 2
  },

  "google_calendar": {
    "enabled": false,
    "calendar_id": "primary",
    "credentials_path": "google_credentials.json",
    "default_duration_hours": 2,
    "send_invites": true
  }
}
